{
    "name": "SituacaoUnidadeSaude",
    "fields": [
        {
            "fieldName": "criacao",
            "fieldType": "Instant",
            "fieldValidateRules": [
                "required"
            ]
        },
        {
            "fieldName": "descricao",
            "fieldType": "String",
            "fieldValidateRules": [
                "required"
            ]
        }
    ],
    "relationships": [],
    "changelogDate": "20191023143837",
    "entityTableName": "situacao_unidade_saude",
    "dto": "mapstruct",
    "pagination": "pagination",
    "service": "serviceImpl",
    "jpaMetamodelFiltering": false,
    "fluentMethods": true,
    "readOnly": false,
    "clientRootFolder": "",
    "applications": "*"
}